arx/__init__.py
arx/__main__.py
arx/cli.py
arx/exceptions.py
arx/io.py
arx/lexer.py
arx/logs.py
arx/main.py
arx/parser.py
arx/semantic.py
arxlang-0.2.0.dist-info/LICENSE
arxlang-0.2.0.dist-info/METADATA
arxlang-0.2.0.dist-info/WHEEL
arxlang-0.2.0.dist-info/entry_points.txt
arxlang-0.2.0.dist-info/RECORD
